[
  {
    "artistid": 1000,
    "keywords": "普通的,命运/冠位指定,Fate/GO 包含 30000 位用户,FGO,间谍×家庭,约尔·福格,SPY×FAMILY 包含 50000 个用户,VOCALOID,初音ミク,包含 VOCALOID 1000 位用户,埃列什基伽勒（泳装）,埃列什基伽勒（命运）",
    "intro": null,
    "users": {
      "userid": 1000,
      "nickname": "ASK"
    }
  },
  {
    "artistid": 1001,
    "keywords": "原神,原神,原神 10000 用户,哥伦宾那 (原神),哥伦比亚,折叠星轨,崩溃：星轨,无禅零区,零零,Zenzero 包括 10000 个用户,桑德隆（原神）,崩坏星轨",
    "intro": null,
    "users": {
      "userid": 1001,
      "nickname": "torino"
    }
  },
  {
    "artistid": 1002,
    "keywords": "原来的,女の子,早乙女志乃,志乃と恋,白雪恋,百合,包含原始1000个用户,着衣巨乳,猫,猫と女の子,包含原始5000个用户,黑色紧身衣",
    "intro": null,
    "users": {
      "userid": 1002,
      "nickname": "千種みのり@お仕事募集中"
    }
  },
  {
    "artistid": 1003,
    "keywords": "原来的,一个美妙而轻松的世界,甜猫,动物食品,喵这个好可爱,猫は液体,包含原始1000个用户,食品 包括 1000 个用户,饺子,寿喜烧,我需要它！！！,寿金烧",
    "intro": null,
    "users": {
      "userid": 1003,
      "nickname": "チャイ"
    }
  },
  {
    "artistid": 1004,
    "keywords": "初音ミク,女の子,原来的,呼啸波涛,鸣潮,Narushio 包含 5000 个用户,VOCALOID,包含 VOCALOID 5000 位用户,初音未来,39,包含 VOCALOID 1000 位用户,原创",
    "intro": null,
    "users": {
      "userid": 1004,
      "nickname": "Li Flag"
    }
  },
  {
    "artistid": 1005,
    "keywords": "普罗塞卡,VOCALOID,懐かしき想い出,包括 Proseca 1000 位用户,投稿時間に愛を感じる,包含 VOCALOID 1000 位用户,凯托,女の子,初音ミク,赔率,小豆沢こはね,足立レイ",
    "intro": null,
    "users": {
      "userid": 1005,
      "nickname": "Sa-fu"
    }
  },
  {
    "artistid": 1006,
    "keywords": "原来的,風景,ゲーム画面風,包含原始5000个用户,巫女,漫画市场107,秋,紅葉,平原,丘,駅,山門",
    "intro": null,
    "users": {
      "userid": 1006,
      "nickname": "あすてろid"
    }
  },
  {
    "artistid": 1007,
    "keywords": "女の子,麦麦,罗塔埃诺,莉兹（麦麦）,原来的,花と女の子,朝顔,初音ミク,VOCALOID,Miku和花,包含 VOCALOID 1000 位用户,胆汁",
    "intro": null,
    "users": {
      "userid": 1007,
      "nickname": "Saclia"
    }
  },
  {
    "artistid": 1008,
    "keywords": "刀剣乱舞,三郎国宗(刀剣乱舞),三郎国宗,本家,命运/冠位指定,FGO,葛葉,虹山寺,铲运机,刀剑乱舞 10000 用户,包含 Fate/GO 1000 位用户,奥布朗（命运）",
    "intro": null,
    "users": {
      "userid": 1008,
      "nickname": "AU"
    }
  },
  {
    "artistid": 1009,
    "keywords": "会社と私生活,开和关,プロの犯行,动漫风格,嘎奇演员,卢多,Gachiactor 包含 1000 个用户,绫行,行明君,女の子,好神秘☆我的弟弟行明君,爆豪勝己",
    "intro": null,
    "users": {
      "userid": 1009,
      "nickname": "金沢真之介"
    }
  },
  {
    "artistid": 1010,
    "keywords": "口袋妖怪,雷中咖啡馆,这宝宝怎么这么可爱？,雷丘日,乌戈伊拉,雷丘看起来也很有趣,调查仍然存在偏见,有偏见的调查,美丽的咖啡馆,雷中,毕竟调查有偏见,不，不是这样的",
    "intro": null,
    "users": {
      "userid": 1010,
      "nickname": "カフェ"
    }
  },
  {
    "artistid": 1011,
    "keywords": "女の子,尘白禁区,雪断,笑顔,崩坏3rd,破雪 1000 位用户,美脚,雀魂,本家,仕事絵,帽,米娅",
    "intro": null,
    "users": {
      "userid": 1011,
      "nickname": "Criin"
    }
  },
  {
    "artistid": 1012,
    "keywords": "原来的,现实有时也会撒谎,ゲーム好きの友達と色々する話,ゲーム好きの彼女と色々する話,指甲油,逢坂七海,包含原始3000个用户,包含原始7500名用户,包含原始5000个用户,虚拟YouTuber,霍洛直播,啦啦队长",
    "intro": null,
    "users": {
      "userid": 1012,
      "nickname": "にいち"
    }
  },
  {
    "artistid": 1013,
    "keywords": "風景,背景,原来的,插图,女の子,創作,空,青空,日本动画片,插图,春,桜",
    "intro": null,
    "users": {
      "userid": 1013,
      "nickname": "まころんコミケ107南g20a"
    }
  },
  {
    "artistid": 1014,
    "keywords": "VOCALOID,初音ミク,脐,漫画,包含 VOCALOID 1000 位用户,叔叔语法,斋发,結月ゆかり,语音机器人,巡音ルカ,什么事这么感动？,发型改变",
    "intro": null,
    "users": {
      "userid": 1014,
      "nickname": "わいもにく"
    }
  },
  {
    "artistid": 1015,
    "keywords": "手鞠,鹿手间,奈良鹿丸,火影忍者,洛丽特玛,口袋妖怪,漫画,同人誌,辣椒（教练）,青木（教练）,蓝辣椒,口袋妖怪SV",
    "intro": null,
    "users": {
      "userid": 1015,
      "nickname": "獅子唐/マツタケ"
    }
  },
  {
    "artistid": 1016,
    "keywords": "歌声,VOCALOID,初音ミク,仕事絵,重音テト,包含 VOCALOID 1000 位用户,名工,初音未来,剪刀,虹山寺,鈴原るる,其实很可怕的尼吉三治",
    "intro": null,
    "users": {
      "userid": 1016,
      "nickname": "ワーワー言うとりま助℃"
    }
  },
  {
    "artistid": 1017,
    "keywords": "女の子,崩坏星穹铁道,折叠星轨,崩坏星轨,白髪,赤眼,悪魔,分享,崩溃：星轨 5000 位用户,原来的,吸血鬼,高跟鞋",
    "intro": null,
    "users": {
      "userid": 1017,
      "nickname": "Sheya"
    }
  },
  {
    "artistid": 1018,
    "keywords": "女の子,VOCALOID,初音ミク,未来,包含 VOCALOID 5000 位用户,逆流茶会,双特,【削除しなさい】困難女性(コンジョ)自警委員会より警告,39,包含 VOCALOID 1000 位用户,2026 年初音未来日,存在感薄い妹との簡単生活",
    "intro": null,
    "users": {
      "userid": 1018,
      "nickname": "千夜QYS3"
    }
  },
  {
    "artistid": 1019,
    "keywords": "订单是兔子吗？,保登心愛,原来的,基拉拉 MAX,日常,业务,我没有取得太大进展，所以我要找个地方过夜。,虚拟YouTuber,VTuber,埃尔登指环：夜雨,口袋妖怪传奇,卡比的空中骑士",
    "intro": null,
    "users": {
      "userid": 1019,
      "nickname": "なまず"
    }
  },
  {
    "artistid": 1020,
    "keywords": "蓝色档案,蓝色档案,布鲁阿卡,調月リオ,爆乳,酷美,内裤,リブ生地,巨大的胸部,調月リオ(臨戦),鋼鉄大陸攻略戦,飛鳥馬トキ",
    "intro": null,
    "users": {
      "userid": 1020,
      "nickname": "Shigure@FANBOX"
    }
  },
  {
    "artistid": 1021,
    "keywords": "VOCALOID,初音ミク,包含 VOCALOID 1000 位用户,初音未来,普罗塞卡,日野森志歩,星乃一歌,包括 Proseca 1000 位用户,2026 年初音未来日,世界计划,世界交响曲,巡音ルカ",
    "intro": null,
    "users": {
      "userid": 1021,
      "nickname": "からながれ"
    }
  },
  {
    "artistid": 1022,
    "keywords": "原来的,实力姐妹,姐姐,原神,悪魔,唇,百合,玛丽亚·哈特韦尔,女悪魔,超级辉夜姬！,辉夜姬（超级辉夜姬！）,酒寄彩葉",
    "intro": null,
    "users": {
      "userid": 1022,
      "nickname": "山本アリフレッド"
    }
  },
  {
    "artistid": 1023,
    "keywords": "原来的,VOCALOID,包含 VOCALOID 1000 位用户,女の子,初音ミク,包含原始1000个用户,白色紧身裤,FGO,军刀,命运,遠坂凛,军刀（星轨）",
    "intro": null,
    "users": {
      "userid": 1023,
      "nickname": "Lpip"
    }
  },
  {
    "artistid": 1024,
    "keywords": "阿尔凯亚,Arcaea1000用户包括在内,野诺卡 (Arcaea),光子 (Arcaea),光（Arcaea）,冲突（Arcaea）,横顔,我想点亮,野野香,光子,手袋,識眼",
    "intro": null,
    "users": {
      "userid": 1024,
      "nickname": "すずなし"
    }
  },
  {
    "artistid": 1025,
    "keywords": "宣伝,花魁系JK,原来的,読み切り,口袋妖怪,口袋妖怪传奇,金丝雀,传奇-A,包括《精灵宝可梦 1000》用户,脳内再生余裕,金丝雀（训练师）,电锯人",
    "intro": null,
    "users": {
      "userid": 1025,
      "nickname": "iPad Pro買ったR君"
    }
  },
  {
    "artistid": 1026,
    "keywords": "插图,原来的,平凡でも非現実でもない日常,代码Geass,超级机器人大战OG,新年,圣诞节,DL販売,告知,今更投稿,祝い事?する価値無し!,城市猎人",
    "intro": null,
    "users": {
      "userid": 1026,
      "nickname": "ぐってぃ"
    }
  },
  {
    "artistid": 1027,
    "keywords": "VOCALOID,初音ミク,包含 VOCALOID 1000 位用户,高跟鞋,初音未来,2026 年初音未来日,现在轮回,无禅零区,禅零,妄想天使,公关,包括 Zenzero 1000 用户",
    "intro": null,
    "users": {
      "userid": 1027,
      "nickname": "甘木花"
    }
  },
  {
    "artistid": 1028,
    "keywords": "初音ミク,VOCALOID,歌声,初音未来,包含 VOCALOID 1000 位用户,初音未来,罗林女孩,哇,苦巧克力装饰,如果未来,白雪公主",
    "intro": null,
    "users": {
      "userid": 1028,
      "nickname": "雪愛"
    }
  },
  {
    "artistid": 1029,
    "keywords": "无禅,禅零,零零,包括 Zenzero 500 用户,逊纳,千夏,姿势狂人向动物学习,明日方舟安德菲尔德,明日方舟終末地,明日方舟恩德菲尔德,生化危机安魂曲,生化危机安魂曲",
    "intro": null,
    "users": {
      "userid": 1029,
      "nickname": "HUE"
    }
  },
  {
    "artistid": 1030,
    "keywords": "VOCALOID,初音ミク,包含 VOCALOID 5000 位用户,初音未来,结束场,明日方舟恩德菲尔德,明日方舟終末地,包括 Endfield 1000 用户,拉埃瓦坦（末场）,最后的光（结束场）,佩里卡（端场）,伊维娜（明日方舟）",
    "intro": null,
    "users": {
      "userid": 1030,
      "nickname": "Ray"
    }
  },
  {
    "artistid": 1031,
    "keywords": "女の子,插图,少女,原来的,大腿,同人,金髪,奥克,白色紧身裤,女佣,方舟之夜,明日方舟",
    "intro": null,
    "users": {
      "userid": 1031,
      "nickname": "Sentter"
    }
  },
  {
    "artistid": 1032,
    "keywords": "原来的,印迹图,寂静岭f,新世纪福音战士,苍龙·明日香·兰利,新世纪福音战士 30 周年,式并明日香·兰利,エヴァンゲリオン放送30周年記念特別興行,新世纪福音战士,包含原始1000个用户,未来日記,我妻由乃",
    "intro": null,
    "users": {
      "userid": 1032,
      "nickname": "ポテトルス"
    }
  },
  {
    "artistid": 1033,
    "keywords": "原来的,おいでよ_魔法少女村(不法占拠),格子布（漫画家）,你是什​​么意思？,我的意思是……你什么意思？,我不明白。,当你看到这个的时候就结束了,推荐点击,見たら最後,训练有素的评论区,魔法少女最高!,4帧",
    "intro": null,
    "users": {
      "userid": 1033,
      "nickname": "ギンガム"
    }
  },
  {
    "artistid": 1034,
    "keywords": "原来的,創作,包含原始1000个用户,花と女の子,春,女の子,民族衣装,魔女,这个日语很可爱,商業作品,魔法,秋",
    "intro": null,
    "users": {
      "userid": 1034,
      "nickname": "淵゛(ぶち)"
    }
  },
  {
    "artistid": 1035,
    "keywords": "虹山寺,花园柴卡,莉兹·海莱斯塔,海莱斯塔兄弟姐妹,包括虚拟 YouTuber 500 用户,包括 100 名虚拟 YouTuber 用户,包括 1000 名虚拟 YouTuber 用户,虹创作11,漫画,二次創作,虹创作10",
    "intro": null,
    "users": {
      "userid": 1035,
      "nickname": "やまんの"
    }
  },
  {
    "artistid": 1036,
    "keywords": "原神,正太,少年,兔子,女装,兔男孩,原神 1000 位用户,腋,凛（原神）,坚一,原神,腋見せ衣装",
    "intro": null,
    "users": {
      "userid": 1036,
      "nickname": "麻理宮ゆう"
    }
  },
  {
    "artistid": 1037,
    "keywords": "原来的,江口酱,VOCALOID,初音ミク,委员会,着物,正月,午年,年賀状2026,和室,緑髪,万圣节",
    "intro": null,
    "users": {
      "userid": 1037,
      "nickname": "えぐえぐ"
    }
  },
  {
    "artistid": 1038,
    "keywords": "VOCALOID,初音ミク,包含 VOCALOID 1000 位用户,巡音ルカ,鏡音リン,鏡音レン,凯托,名工,佐仓未来,2026 年初音未来日,包括 VOCALOID100 用户,6氪兄弟",
    "intro": null,
    "users": {
      "userid": 1038,
      "nickname": "にわ子"
    }
  },
  {
    "artistid": 1039,
    "keywords": "原来的,女の子,女子校生,脐,自撮り,手机,睡衣,初音ミク,VOCALOID,初音未来,包含 VOCALOID 1000 位用户,制服",
    "intro": null,
    "users": {
      "userid": 1039,
      "nickname": "天三月"
    }
  },
  {
    "artistid": 1040,
    "keywords": "如何留住一个人,赤鼻の旅人,这是UMA,愤怒的埃扎克,←如果再打更小的盖卡，会发生什么……？,路地裏,池雄路",
    "intro": null,
    "users": {
      "userid": 1040,
      "nickname": "ぴえ太"
    }
  },
  {
    "artistid": 1041,
    "keywords": "VOCALOID,女の子,初音ミク,原来的,包含 VOCALOID 1000 位用户,兔子洞,兔女郎,手錠,足立レイ,TAU,熱異常,伊予和",
    "intro": null,
    "users": {
      "userid": 1041,
      "nickname": "檀上大空"
    }
  },
  {
    "artistid": 1042,
    "keywords": "食べ物,食品恐怖主义,pixiv食堂,食品 包含 100 位用户,食品 包含 500 位用户,食物插图,pixiv咖啡厅,食品 包括 1000 个用户,和菓子,原来的,餃子,真实图片",
    "intro": null,
    "users": {
      "userid": 1042,
      "nickname": "晴菜"
    }
  },
  {
    "artistid": 1043,
    "keywords": "柿太郎,津太郎,杜小畑（训练员）,太郎（训练师）,爱丽丝（神奇宝贝）,包括《精灵宝可梦 1000》用户,柿子,月が綺麗だね,苏瓜,哈尔西,佩帕博塔,太精彩了",
    "intro": null,
    "users": {
      "userid": 1043,
      "nickname": "もなこ@新刊予約受付中"
    }
  },
  {
    "artistid": 1044,
    "keywords": "斯克布,原来的,原创角色,創作,帅气的女孩,电锯人,传治,电锯侠（电锯侠）,雷泽,雷泽（电锯侠）,登雷塞,银河铁道Milky☆地铁",
    "intro": null,
    "users": {
      "userid": 1044,
      "nickname": "eba"
    }
  },
  {
    "artistid": 1045,
    "keywords": "原来的,女の子,金髪,初音ミク,VOCALOID,初音未来,2026 年初音未来日,年賀絵,創作,午年,年賀状2026,万圣节",
    "intro": null,
    "users": {
      "userid": 1045,
      "nickname": "午前十時雨"
    }
  },
  {
    "artistid": 1046,
    "keywords": "袜底,裸足,女の子,足裏,内裤,黑色紧身衣,OL,足指,白色紧身裤,修脚,原来的,兽耳",
    "intro": null,
    "users": {
      "userid": 1046,
      "nickname": "qizhu"
    }
  },
  {
    "artistid": 1047,
    "keywords": "初音ミク,VOCALOID,初音未来,包含 VOCALOID 5000 位用户,初音未来,包含 VOCALOID 1000 位用户,初音未來,美ク,初音ミク誕生祭2025,魔卡少女樱,包括 CLAMP 500 位用户,木之本桜",
    "intro": null,
    "users": {
      "userid": 1047,
      "nickname": "歐MIN"
    }
  },
  {
    "artistid": 1048,
    "keywords": "初音ミク,委员会,原来的,少年,VOCALOID,包含 VOCALOID 1000 位用户,艺术,伊纳托,重音テト,好我的拉康 10 Miku,女の子,少女",
    "intro": null,
    "users": {
      "userid": 1048,
      "nickname": "kiri"
    }
  },
  {
    "artistid": 1049,
    "keywords": "創作,翔太凉奈,小人リョナ,男 ryona,正太,創作BL,跟踪者,赤脚",
    "intro": null,
    "users": {
      "userid": 1049,
      "nickname": "三谷"
    }
  },
  {
    "artistid": 1050,
    "keywords": "原来的,花子在厕所,女の子,花子同学，别吃。,舔舌头,食品恐怖主义,脂肪フラグ,拉面,梅希的脸,夢皮呉葉,巨乳,妃崎メイリ",
    "intro": null,
    "users": {
      "userid": 1050,
      "nickname": "茸谷きの子"
    }
  },
  {
    "artistid": 1051,
    "keywords": "少女,原来的,包含原始5000个用户,萝莉,黒髪,水手服,女の子,吊带背心,内裤,围巾,貧乳,制服",
    "intro": null,
    "users": {
      "userid": 1051,
      "nickname": "あきぺこ"
    }
  },
  {
    "artistid": 1052,
    "keywords": "漫画,創作BL,原来的,創作,工字平衡,体操着,体育着,兔子,欺负",
    "intro": null,
    "users": {
      "userid": 1052,
      "nickname": "かわも"
    }
  },
  {
    "artistid": 1053,
    "keywords": "背景,女の子,風景,原来的,女佣,博麗霊夢,少名針妙丸,东方Project,幼女戦記,坦尼娅·德古雷查夫,軍艦,坦尼娅",
    "intro": null,
    "users": {
      "userid": 1053,
      "nickname": "こうこうや"
    }
  },
  {
    "artistid": 1054,
    "keywords": "漫画,雪折间仅限一晚,通常,存在しない記憶,大根怪人,ヤギ大根,鉄拳正妻,翔太一号,NTR？,腋,顶浆汗腺,我々の業界ではご褒美です",
    "intro": null,
    "users": {
      "userid": 1054,
      "nickname": "ハミタ"
    }
  },
  {
    "artistid": 1055,
    "keywords": "巨乳,淫荡的身体,蔚蓝巷,魅惑の谷間,碧蓝航线 1000 位用户,车轮先睹为快,包括碧蓝航线 5000 位用户,巨大的胸部,勝利の女神:NIKKE,萤石（端场）,明日方舟：恩菲尔德,连体衣",
    "intro": null,
    "users": {
      "userid": 1055,
      "nickname": "E.C.HO"
    }
  },
  {
    "artistid": 1056,
    "keywords": "FGO,命运/冠位指定,女の子,包含 Fate/GO 1000 位用户,原来的,笑顔,包含原始5000个用户,黑色罢工,遠坂凛,五大元素使い,阿纳斯塔西娅,阿纳斯塔西娅·尼古拉耶芙娜·罗曼诺娃（命运）",
    "intro": null,
    "users": {
      "userid": 1056,
      "nickname": "Bison倉鼠"
    }
  },
  {
    "artistid": 1057,
    "keywords": "男の娘,奥克,原来的,VOCALOID,初音ミク,双马尾,初音未来,創作,眼帯,哥特洛丽塔,超级辉夜姬！,辉夜姬（超级辉夜姬！）",
    "intro": null,
    "users": {
      "userid": 1057,
      "nickname": "誇り高き埃"
    }
  },
  {
    "artistid": 1058,
    "keywords": "女の子,蓝色档案,布鲁阿卡,无禅零区,Blue Archive 包含 1000 个用户,原神,芙蕾娜（原神）,原神 1000 位用户,艾伦·乔,ZenlessZoneZero,艾伦·乔：周一至周五,後ろ姿",
    "intro": null,
    "users": {
      "userid": 1058,
      "nickname": "SushiSpin"
    }
  },
  {
    "artistid": 1059,
    "keywords": "虹山寺,葛葉,多拉（虹山寺）,社築,ド葛本社,包括虚拟 YouTuber 500 用户,本间向日葵,包括 1000 名虚拟 YouTuber 用户,加賀美ハヤト,黑之轮,叶,铬诺伊R",
    "intro": null,
    "users": {
      "userid": 1059,
      "nickname": "まぶし"
    }
  },
  {
    "artistid": 1060,
    "keywords": "原神,原神,弗里娜,哥伦宾那 (原神),女の子,原神 1000 位用户,裙子,原神 5000 用户,换装,美脚,桜,お花見",
    "intro": null,
    "users": {
      "userid": 1060,
      "nickname": "雲小猫"
    }
  },
  {
    "artistid": 1061,
    "keywords": "服装布置,鼠标图片,东方project,東方,东方Project 包含250名用户,博麗霊夢,东方Project 100名用户,东方Project 500名用户,古明地こいし,VOCALOID,初音ミク,包括 VOCALOID100 用户",
    "intro": null,
    "users": {
      "userid": 1061,
      "nickname": "原野香久山"
    }
  },
  {
    "artistid": 1062,
    "keywords": "SCP,SCP_基金会,女の子,SCP 快速介绍,山雀,X战警,奇迹,C107,希少種転生,C105,包括 SCP100 用户,杀手！",
    "intro": null,
    "users": {
      "userid": 1062,
      "nickname": "松(A・TYPEcorp.)"
    }
  },
  {
    "artistid": 1063,
    "keywords": "犬,漫画,可能就是这只侦探狗。,喜剧,口袋妖怪,叔叔,口袋妖怪风波,波姆肯,狗口袋妖怪,包括《精灵宝可梦 1000》用户,雑記,乌戈伊拉",
    "intro": null,
    "users": {
      "userid": 1063,
      "nickname": "ヤシン/マンガ連載中"
    }
  },
  {
    "artistid": 1064,
    "keywords": "圆切,百合,原神,真木由香,結月ゆかり,弦巻マキ,刻甘,甘刻,语音机器人,VOICEROID 包含 100 位用户,Genshin 包含 100 位用户,C100",
    "intro": null,
    "users": {
      "userid": 1064,
      "nickname": "マケー"
    }
  },
  {
    "artistid": 1065,
    "keywords": "女の子,VOCALOID,初音ミク,私の本気,包含 VOCALOID 1000 位用户,初音未来,2026 年初音未来日,高跟鞋,初音ミク誕生祭2025,神奇的未来,我不觉得我能赢,佐仓未来",
    "intro": null,
    "users": {
      "userid": 1065,
      "nickname": "あさひクロイ"
    }
  },
  {
    "artistid": 1066,
    "keywords": "女の子,原来的,Kinako（不喜欢面包）,我的猫是个女孩，很可爱,讨厌面包,在这个系列中，我希望你一边给我看你的内裤，一边看我的坏脸。,内裤,黄子（真实型）,猫耳,C107,漫画市场107,初音ミク",
    "intro": null,
    "users": {
      "userid": 1066,
      "nickname": "40原"
    }
  },
  {
    "artistid": 1067,
    "keywords": "包括 Endfield 1000 用户,崩坏星轨,折叠星轨,佩里卡（端场）,崩溃：星轨 500 位用户,笑顔,结束场,手袋,克莫米米,埃瓦内西亚,斯帕西,白发",
    "intro": null,
    "users": {
      "userid": 1067,
      "nickname": "Asiri Senpai"
    }
  },
  {
    "artistid": 1068,
    "keywords": "绘画,少女,绘画,画,創作,插图,裙子,女の子,裙子,洛可可",
    "intro": null,
    "users": {
      "userid": 1068,
      "nickname": "YHM"
    }
  },
  {
    "artistid": 1069,
    "keywords": "女の子,制服,学生,原来的,迷你角色,落書き,数字的,我尝试画它,初音未来,初音ミク,VOCALOID,歌声",
    "intro": null,
    "users": {
      "userid": 1069,
      "nickname": "逢坂レイ@お仕事募集中"
    }
  },
  {
    "artistid": 1070,
    "keywords": "初音ミク,VOCALOID,包含 VOCALOID 1000 位用户,女の子,三原光和,天使,pixiv樱花效应,原来的,佐仓未来,包含 VOCALOID 500 位用户,包括 VOCALOID100 用户,矯正っ娘",
    "intro": null,
    "users": {
      "userid": 1070,
      "nickname": "balabling"
    }
  },
  {
    "artistid": 1071,
    "keywords": "原神,原神,伊法,伊法,莱里尔,坚一,奥洛伦,蛍(原神),褐色,塞斯利河,法尔卡（原神）,汗",
    "intro": null,
    "users": {
      "userid": 1071,
      "nickname": "ᴘᴇɴᴢɪ"
    }
  },
  {
    "artistid": 1072,
    "keywords": "加仑,黑妞,日本刀,宽松的袜子,VOCALOID,电锯人,力量,林奈,鳴潮,呼啸波涛,指甲油,包含原始1000个用户",
    "intro": null,
    "users": {
      "userid": 1072,
      "nickname": "𝗺𝗮𝗼"
    }
  },
  {
    "artistid": 1073,
    "keywords": "原来的,女の子,創作,白髪,惠安,Huion创作,翼,ヰ世界情緒,歌手,包括虚拟 YouTuber 500 用户,万圣节",
    "intro": null,
    "users": {
      "userid": 1073,
      "nickname": "yuzuお仕事募集中"
    }
  },
  {
    "artistid": 1074,
    "keywords": "鸣潮,莫宁,白髪,赤眼,包含 Narushio 1000 个用户,片目隠れ,角娘,恩菲尔德,包括 Endfield 1000 用户,莫尼尔,裸露,明日方舟",
    "intro": null,
    "users": {
      "userid": 1074,
      "nickname": "Leria_V"
    }
  },
  {
    "artistid": 1075,
    "keywords": "原神,原神,原神 1000 位用户,南和杏,東品華,工字平衡,包含原始500个用户,文体（原神）,催眠,催眠術,少女与战车,安藤 (GuP)",
    "intro": null,
    "users": {
      "userid": 1075,
      "nickname": "冬鳥ユキノ"
    }
  },
  {
    "artistid": 1076,
    "keywords": "百合,原来的,創作百合,包含 Yuri 1000 个用户,女の子,包含原始1000个用户,女同性恋,漂白,包括 BLEACH1000 用户,漫画,創作漫画,褐色",
    "intro": null,
    "users": {
      "userid": 1076,
      "nickname": "ぱんだこりゃ"
    }
  },
  {
    "artistid": 1077,
    "keywords": "原来的,插图,創作,人生優勝物語,叽叽喳喳,YouTube,創作男女,日本动画片,空岛_工作室,久しぶりに会った人が人生優勝してた,电锯人,插图",
    "intro": null,
    "users": {
      "userid": 1077,
      "nickname": "影山凌空＠マンガ"
    }
  },
  {
    "artistid": 1078,
    "keywords": "VOCALOID,初音ミク,春,桜,原来的,崇拜,水,包括 VOCALOID100 用户,義足,2026 年初音未来日,過学習,女の子",
    "intro": null,
    "users": {
      "userid": 1078,
      "nickname": "ア行 / Agyou"
    }
  },
  {
    "artistid": 1079,
    "keywords": "插图,原来的,女の子,杏夜くもり,創作,TSF,女体化,女装男子,虚拟YouTuber,Vtuber,水着,合作",
    "intro": null,
    "users": {
      "userid": 1079,
      "nickname": "maka/西島世那"
    }
  },
  {
    "artistid": 1080,
    "keywords": "包括 Endfield 1000 用户,原神,罗西（端场）,罗西娜·狼珍珠·卢皮诺,明日方舟：恩菲尔德,原神 1000 位用户,无禅零区,包括 Zenzero 1000 用户,瓦莱萨,哥伦宾那 (原神),桑德隆（原神）,科罗桑",
    "intro": null,
    "users": {
      "userid": 1080,
      "nickname": "ゆうひどら"
    }
  },
  {
    "artistid": 1081,
    "keywords": "水星の魔女,特雷塔·水星,山田一族。,高达,米奥林·伦布兰克,机动战士高达GQuuuuuuX,埃里克·萨玛亚,狸,狐,浣熊的时代结束了,马楚,天手柚叶",
    "intro": null,
    "users": {
      "userid": 1081,
      "nickname": "山田一族。"
    }
  },
  {
    "artistid": 1082,
    "keywords": "紧身套装,橡胶套装,気密服,适合YouTuber,薄荷幻影,旗袍衣服,面具,MIX（Aquarion EVOL）,Aquarion EVOL,芭芭拉（蓝色档案）,堕落,布鲁阿卡",
    "intro": null,
    "users": {
      "userid": 1082,
      "nickname": "まぐろ２７"
    }
  },
  {
    "artistid": 1083,
    "keywords": "勝利の女神:NIKKE,包括 NIKKE5000 用户,汗,お尻,原创角色,原来的,指甲油,龙女,尻尾,爆乳,斯克布,伊冯（恩德菲尔德）",
    "intro": null,
    "users": {
      "userid": 1083,
      "nickname": "TEDDY"
    }
  },
  {
    "artistid": 1084,
    "keywords": "虚拟YouTuber,虹山寺,VTuber,包括虚拟 YouTuber 500 用户,夜見れな,魔界之利里梦,包括 100 名虚拟 YouTuber 用户,石神のぞみ,哇,女の子,瑞纳的鸟素描,粉色和黑色",
    "intro": null,
    "users": {
      "userid": 1084,
      "nickname": "me"
    }
  },
  {
    "artistid": 1085,
    "keywords": "蓝色档案,蓝色档案,布鲁阿卡,女の子,温泉,Blue Archive 包含 10000 个用户,Blue Archive 包含 5000 个用户,竜華キサキ,木崎（蓝色档案）,黑色胸罩,浴衣,凉鞋",
    "intro": null,
    "users": {
      "userid": 1085,
      "nickname": "Pepa"
    }
  },
  {
    "artistid": 1086,
    "keywords": "超级辉夜姬！,卡吉罗,百合,超级辉夜姬！包括 1000 个用户,超级辉夜姬！包含 500 位用户",
    "intro": null,
    "users": {
      "userid": 1086,
      "nickname": "わがりろ"
    }
  },
  {
    "artistid": 1087,
    "keywords": "原神,原神,折叠星轨,崩坏星轨,伊内法,崩溃：Star Rail 1000 个用户,崩溃：星轨 500 位用户,伊内法,纳德·克莱,原神 1000 位用户,艾诺（原神）,兹白",
    "intro": null,
    "users": {
      "userid": 1087,
      "nickname": "もなか食"
    }
  },
  {
    "artistid": 1088,
    "keywords": "世界计划,普罗塞卡,初音ミク,日野森雫,初音未来,星乃一歌,VOCALOID,巡音ルカ,2026 年初音未来日,草薙寧々,2025 年初音未来日,吉他",
    "intro": null,
    "users": {
      "userid": 1088,
      "nickname": "つちのどこ"
    }
  },
  {
    "artistid": 1089,
    "keywords": "佐伯睡着了,女の子,粉丝艺术,七つの大罪,国王,激辛お嬢さまは自分を罰したい,原来的,姉弟,水曜姉弟,黛安,七大罪,货车",
    "intro": null,
    "users": {
      "userid": 1089,
      "nickname": "小菊路 『ヴォカライズ』"
    }
  },
  {
    "artistid": 1090,
    "keywords": "美少女,女の子,大腿,少女,零零,禅零,ZenlessZoneZero,裙子,妄想天使,原神,原神,原神冲击",
    "intro": null,
    "users": {
      "userid": 1090,
      "nickname": "songpyeon"
    }
  },
  {
    "artistid": 1091,
    "keywords": "奥克,原来的,初音ミク,恩菲尔德,初音未来,2026 年初音未来日,西三注,阿尔达希尔,结束场,pixiv情人节效应,德米库 LIVE2026,包含 VOCALOID 1000 位用户",
    "intro": null,
    "users": {
      "userid": 1091,
      "nickname": "ユカン"
    }
  },
  {
    "artistid": 1092,
    "keywords": "原来的,迪亚_创造,VOCALOID,初音ミク,仕事絵,熔化,東方,東方幻想エクリプス,姫海棠はたて,年賀状,着物,圣诞节",
    "intro": null,
    "users": {
      "userid": 1092,
      "nickname": "saihate"
    }
  },
  {
    "artistid": 1093,
    "keywords": "VOCALOID,初音ミク,仕事絵,包含 VOCALOID 1000 位用户,2026 年初音未来日,初音未来,海,ATRI,水中,初音ミク誕生祭2025,初音ミク生誕祭2025,絶対領域",
    "intro": null,
    "users": {
      "userid": 1093,
      "nickname": "奏音"
    }
  },
  {
    "artistid": 1094,
    "keywords": "女の子,插图,原来的,原创角色,猫耳,克莫耳,包含原始500个用户,包含原始300个用户,巧克力,绑带鞋,猫と女の子,魔法少女",
    "intro": null,
    "users": {
      "userid": 1094,
      "nickname": "西条"
    }
  },
  {
    "artistid": 1095,
    "keywords": "創作BL,原来的,FGO,包含 Fate/GO 1000 位用户,孤岛,J庭58,嘉园58,漫画,注意,非常感谢，,多么可爱的男孩啊,拜托，请把它写成书吧！",
    "intro": null,
    "users": {
      "userid": 1095,
      "nickname": "もぞなぎ"
    }
  },
  {
    "artistid": 1096,
    "keywords": "虹山寺,栞葉るり,甘草反冲,瑞科瑞科,錦木千束,井上泷菜,千佐泷,超级辉夜姬！,辉夜姬（超级辉夜姬！）,酒寄彩葉,月見ヤチヨ,卡吉罗",
    "intro": null,
    "users": {
      "userid": 1096,
      "nickname": "古本屋"
    }
  },
  {
    "artistid": 1097,
    "keywords": "宵崎奏,金间府,软吗？,麻风奏,朝比奈まふゆ,尼戈·凯特,我想知道凯是否,江中名,金名,淡水,金水,奏愛され",
    "intro": null,
    "users": {
      "userid": 1097,
      "nickname": "メロン"
    }
  },
  {
    "artistid": 1098,
    "keywords": "歌声,VOCALOID,初音ミク,重音テト,TAU,歌声,年轮蛋糕 Endrol,亞北ネル,初音未来,地球の裏,伊俄瓦女孩,伊予和",
    "intro": null,
    "users": {
      "userid": 1098,
      "nickname": "アマネレイ"
    }
  },
  {
    "artistid": 1099,
    "keywords": "原来的,女の子,VOCALOID,包含原始500个用户,初音ミク,哥特洛丽塔,名侦探普库亚！,治愈奥术暗影,森亜るるか,包括 Tanpuri 500 位用户,銀髪,天使",
    "intro": null,
    "users": {
      "userid": 1099,
      "nickname": "ぱる野"
    }
  }
]